README.rst
setup.py
metu_cafeteria_menu/__init__.py
metu_cafeteria_menu/exceptions.py
metu_cafeteria_menu/utils.py
metu_cafeteria_menu.egg-info/PKG-INFO
metu_cafeteria_menu.egg-info/SOURCES.txt
metu_cafeteria_menu.egg-info/dependency_links.txt
metu_cafeteria_menu.egg-info/not-zip-safe
metu_cafeteria_menu.egg-info/requires.txt
metu_cafeteria_menu.egg-info/top_level.txt