Metadata-Version: 1.1
Name: metu-cafeteria-menu
Version: 0.0.4
Summary: A utility for fetching Middle East Technical University's cafeteria menu.
Home-page: https://github.com/th0th/metu-cafeteria-menu
Author: Gökhan Sarı
Author-email: me@th0th.me
License: MIT
Download-URL: https://github.com/th0th/metu-cafeteria-menu/tarball/0.0.4
Keywords: metu,cafeteria,menu
Platform: UNKNOWN
